tweet_matcher/__init__.py
tweet_matcher/config.py
tweet_matcher/matcher.py
tweet_matcher/utils.py
tweet_matcher-1.0.1.dist-info/METADATA
tweet_matcher-1.0.1.dist-info/WHEEL
tweet_matcher-1.0.1.dist-info/top_level.txt
tweet_matcher-1.0.1.dist-info/RECORD
