Metadata-Version: 2.1
Name: tweet-matcher
Version: 1.0.1
Summary: Describe your package in one sentence
Home-page: https://github.com/dlgiant/tweet_matcher
Author: Ricardo Nunes
Author-email: sanunes.ricardo@gmail.com
License: Apache License 2.0
Platform: UNKNOWN
Requires-Dist: jsonlines
Requires-Dist: pytest
